poetry_plugin_limerick/__init__.py
poetry_plugin_limerick/command.py
poetry_plugin_limerick/limerick/COOKIECUTTER-LICENSE
poetry_plugin_limerick/limerick/__init__.py
poetry_plugin_limerick/limerick/config.py
poetry_plugin_limerick/limerick/environment.py
poetry_plugin_limerick/limerick/exceptions.py
poetry_plugin_limerick/limerick/extensions.py
poetry_plugin_limerick/limerick/find.py
poetry_plugin_limerick/limerick/generate.py
poetry_plugin_limerick/limerick/hooks.py
poetry_plugin_limerick/limerick/main.py
poetry_plugin_limerick/limerick/prompt.py
poetry_plugin_limerick/limerick/replay.py
poetry_plugin_limerick/limerick/repository.py
poetry_plugin_limerick/limerick/utils.py
poetry_plugin_limerick/limerick/vcs.py
poetry_plugin_limerick/limerick/zipfile.py
poetry_plugin_limerick/plugins.py
poetry_plugin_limerick-0.1.1.dist-info/METADATA
poetry_plugin_limerick-0.1.1.dist-info/WHEEL
poetry_plugin_limerick-0.1.1.dist-info/entry_points.txt
poetry_plugin_limerick-0.1.1.dist-info/RECORD
