Metadata-Version: 2.1
Name: poetry-plugin-limerick
Version: 0.1.1
Summary: Plug cookiecutter into poetry!
Author: landowark
Author-email: lando.wark@gmail.com
Requires-Python: >=3.10,<4.0
Classifier: Programming Language :: Python :: 3
Classifier: Programming Language :: Python :: 3.10
Classifier: Programming Language :: Python :: 3.11
Requires-Dist: Jinja2 (>=3,<4)
Requires-Dist: binaryornot (>=0.4.4,<0.5.0)
Requires-Dist: click (>=8,<9)
Requires-Dist: dulwich (>=0.20.50,<0.21.0)
Requires-Dist: jinja2-time (>=0.2.0,<0.3.0)
Requires-Dist: python-slugify (>=4.0.0,<5.0.0)
Requires-Dist: pyyaml (>=5.3.1,<6.0.0)
Requires-Dist: requests (>=2.23.0,<3.0.0)
